predictram_stock_data/__init__.py
predictram_stock_data/iip.py
predictram_stock_data/stock.py
predictram_stock_data-1.0.6.dist-info/METADATA
predictram_stock_data-1.0.6.dist-info/WHEEL
predictram_stock_data-1.0.6.dist-info/top_level.txt
predictram_stock_data-1.0.6.dist-info/RECORD
