Metadata-Version: 2.1
Name: predictram_stock_data
Version: 1.0.6
Summary: The `predictram_stock_data` package provides functionality to load and process stock data and economic indicators such as the Index of Industrial Production (IIP). The package includes functions to retrieve stock data for specific stocks, filter by date range, and load IIP data.
Author: PredictRam
Author-email: support@predictram.com
Requires-Dist: pandas
Requires-Dist: openpyxl
